{
  "facility_id": "hun-b-kk-br-ny-coal-mine-fac",
  "name": "B\u00c3\u00bckk\u00c3\u00a1br\u00c3\u00a1ny Coal Mine",
  "aliases": [
    "B\u00c3\u00bckk\u00c3\u00a1br\u00c3\u00a1ny Coal Mine",
    "B\u00c3\u00bckk\u00c3\u00a1br\u00c3\u00a1ny"
  ],
  "country_iso3": "HUN",
  "location": {
    "lat": 47.89,
    "lon": 20.714,
    "precision": "site"
  },
  "types": [
    "mine"
  ],
  "commodities": [
    {
      "metal": "thermal coal",
      "primary": true
    }
  ],
  "status": "unknown",
  "products": [],
  "sources": [
    {
      "type": "mines_csv",
      "row": 5450
    }
  ],
  "verification": {
    "status": "csv_imported",
    "confidence": 0.85,
    "last_checked": "2025-10-12T19:43:44.237876",
    "checked_by": "migration_script"
  }
}