{
  "facility_id": "zwe-zimasco-mines-fac",
  "name": "**Zimasco Mines**",
  "aliases": [],
  "country_iso3": "ZWE",
  "location": {
    "lat": null,
    "lon": null,
    "precision": "unknown"
  },
  "types": [
    "mine"
  ],
  "commodities": [],
  "status": "operating",
  "company_mentions": [
    "Sinosteel Corporation",
    "Zimasco Pvt Ltd"
  ],
  "products": [],
  "sources": [
    {
      "type": "csv_import",
      "id": "Deep Research 2025",
      "date": "2025-10-21T13:04:39.413358"
    }
  ],
  "verification": {
    "status": "csv_imported",
    "confidence": 0.5,
    "last_checked": "2025-11-04T19:18:51.955551Z",
    "checked_by": "import_pipeline",
    "notes": "Canonical name+slug generated"
  },
  "canonical_name": "Zimasco Mines Mine",
  "canonical_slug": "zimasco-mines-mine",
  "display_name": "Zimasco Mines",
  "primary_type": "mine",
  "type_confidence": 1.0,
  "data_quality": {
    "canonicalization_confidence": 0.615,
    "flags": {
      "town_missing": true,
      "operator_unresolved": false,
      "canonical_name_incomplete": false
    }
  },
  "canonical_name_history": [
    {
      "name": "**Zimasco Mines** Mine",
      "from": "2025-10-21T13:04:39.413361",
      "to": "2025-11-04T19:18:51.955549Z",
      "reason": "data_correction"
    }
  ],
  "display_name_source": "auto",
  "province": "Midlands",
  "enrichment_notes": {
    "web_search_companies": {
      "timestamp": "2025-12-01T16:40:14.000000Z",
      "operators": [
        "Zimasco Pvt Ltd"
      ],
      "owners": [
        "Sinosteel Corporation"
      ],
      "notes": "Zimasco is majority owned by Sinosteel Corporation, a Chinese state-owned enterprise."
    }
  }
}