{
  "facility_id": "ncl-mt-isa-mine-fac",
  "name": "Mt. Isa Mine",
  "aliases": [],
  "country_iso3": "NCL",
  "location": {
    "lat": -22.57,
    "lon": 144.547,
    "precision": "site"
  },
  "types": [
    "mine"
  ],
  "commodities": [
    {
      "metal": "Copper",
      "primary": true
    },
    {
      "metal": "Nickel",
      "primary": false
    },
    {
      "metal": "tin",
      "primary": false
    },
    {
      "metal": "Tungsten",
      "primary": false
    }
  ],
  "status": "unknown",
  "company_mentions": [],
  "products": [],
  "sources": [
    {
      "type": "csv_import",
      "id": "Mines.csv Run 1",
      "date": "2025-10-20T15:26:53.015470"
    }
  ],
  "verification": {
    "status": "csv_imported",
    "confidence": 0.3,
    "last_checked": "2025-10-20T15:26:53.015477",
    "checked_by": "import_pipeline",
    "notes": null
  }
}