{
  "facility_id": "esp-transaccion-fac",
  "name": "Transaccion",
  "aliases": [
    "Transaccion"
  ],
  "country_iso3": "ESP",
  "location": {
    "lat": 36.858,
    "lon": -2.061,
    "precision": "site"
  },
  "types": [
    "mine"
  ],
  "commodities": [
    {
      "metal": "gold",
      "primary": true
    }
  ],
  "status": "unknown",
  "products": [],
  "sources": [
    {
      "type": "mines_csv",
      "row": 8402
    }
  ],
  "verification": {
    "status": "csv_imported",
    "confidence": 0.65,
    "last_checked": "2025-10-12T19:43:44.456489",
    "checked_by": "migration_script"
  }
}