{
  "facility_id": "bgr-elatzite-fac",
  "name": "Elatzite",
  "aliases": [],
  "country_iso3": "BGR",
  "location": {
    "lat": 42.749,
    "lon": 24.502,
    "precision": "site"
  },
  "types": [
    "mine"
  ],
  "commodities": [
    {
      "metal": "Copper",
      "primary": true
    }
  ],
  "status": "unknown",
  "company_mentions": [
    "Ellatzite-Med AD"
  ],
  "products": [],
  "sources": [
    {
      "type": "csv_import",
      "id": "Mines.csv Run 1",
      "date": "2025-10-20T15:26:46.925068"
    }
  ],
  "verification": {
    "status": "csv_imported",
    "confidence": 0.3,
    "last_checked": "2025-11-04T19:18:58.771056Z",
    "checked_by": "import_pipeline",
    "notes": "Canonical name+slug generated"
  },
  "canonical_name": "Elatzite Mine",
  "canonical_slug": "elatzite-mine",
  "display_name": "Elatzite",
  "primary_type": "mine",
  "type_confidence": 1.0,
  "data_quality": {
    "canonicalization_confidence": 0.51,
    "flags": {
      "town_missing": true,
      "operator_unresolved": false,
      "canonical_name_incomplete": true
    }
  },
  "display_name_source": "auto",
  "province": "Sofia",
  "enrichment_notes": {
    "web_search_companies": {
      "timestamp": "2025-11-26T09:13:45.000000Z",
      "operators": [
        "Ellatzite-Med AD"
      ],
      "owners": [
        "Ellatzite-Med AD"
      ],
      "notes": "Ellatzite-Med AD is a private joint stock company involved in mining and dressing of copper and gold-containing ores."
    }
  }
}