{
  "facility_id": "al-prrenjas-mines-see-names-fac",
  "name": "Prrenjas Mines (See Names)",
  "aliases": [],
  "country_iso3": "AL",
  "location": {
    "lat": 41.099,
    "lon": 20.535,
    "precision": "site"
  },
  "types": [
    "mine"
  ],
  "commodities": [
    {
      "metal": "nickel",
      "primary": true
    },
    {
      "metal": "cobalt",
      "primary": false
    }
  ],
  "status": "unknown",
  "owner_links": [],
  "operator_link": null,
  "products": [],
  "sources": [
    {
      "type": "mines_csv",
      "row": 1421
    }
  ],
  "verification": {
    "status": "csv_imported",
    "confidence": 0.2,
    "last_checked": "2025-10-12T19:43:43.161905",
    "checked_by": "migration_script"
  }
}