{
  "facility_id": "chn-maomaoshan-coal-mine-fac",
  "name": "Maomaoshan Coal Mine",
  "aliases": [
    "Maomaoshan Coal Mine",
    "Datong Donggou Coal Mine"
  ],
  "country_iso3": "CHN",
  "location": {
    "lat": 39.841,
    "lon": 112.875,
    "precision": "site"
  },
  "types": [
    "mine"
  ],
  "commodities": [
    {
      "metal": "metallurgical coal",
      "primary": true
    }
  ],
  "status": "unknown",
  "company_mentions": [],
  "products": [],
  "sources": [
    {
      "type": "csv_import",
      "id": "Mines.csv Run 1",
      "date": "2025-10-20T15:27:46.858564"
    }
  ],
  "verification": {
    "status": "csv_imported",
    "confidence": 0.65,
    "last_checked": "2025-11-04T19:18:46.854827Z",
    "checked_by": "import_pipeline",
    "notes": "Canonical name+slug generated"
  },
  "canonical_name": "Maomaoshan Coal Mine",
  "canonical_slug": "maomaoshan-coal-mine",
  "display_name": "Maomaoshan Coal",
  "primary_type": "mine",
  "type_confidence": 1.0,
  "data_quality": {
    "canonicalization_confidence": 0.615,
    "flags": {
      "town_missing": true,
      "operator_unresolved": false,
      "canonical_name_incomplete": true
    }
  },
  "display_name_source": "auto"
}
