{
  "facility_id": "chn-wangpo-coal-mine-fac",
  "name": "Wangpo Coal Mine",
  "aliases": [
    "Wangpo Coal Mine",
    "Dayang Coal Mine",
    "Hongxiang Coal Mine",
    "Shanxi Tian'tai Herui Coal Mine",
    "Dayang",
    "Wangpo"
  ],
  "country_iso3": "CHN",
  "location": {
    "lat": 35.672,
    "lon": 112.741,
    "precision": "site"
  },
  "types": [
    "mine"
  ],
  "commodities": [
    {
      "metal": "thermal coal",
      "primary": true
    }
  ],
  "status": "unknown",
  "company_mentions": [],
  "products": [],
  "sources": [
    {
      "type": "csv_import",
      "id": "Mines.csv Run 1",
      "date": "2025-10-20T15:28:00.210965"
    }
  ],
  "verification": {
    "status": "csv_imported",
    "confidence": 0.8,
    "last_checked": "2025-11-04T19:18:46.809022Z",
    "checked_by": "import_pipeline",
    "notes": "Canonical name+slug generated"
  },
  "canonical_name": "Wangpo Coal Mine",
  "canonical_slug": "wangpo-coal-mine",
  "display_name": "Wangpo Coal",
  "primary_type": "mine",
  "type_confidence": 1.0,
  "data_quality": {
    "canonicalization_confidence": 0.615,
    "flags": {
      "town_missing": true,
      "operator_unresolved": false,
      "canonical_name_incomplete": true
    }
  },
  "display_name_source": "auto"
}