{
  "facility_id": "chn-zijin-smelter-fac",
  "name": "Zijin smelter",
  "aliases": [],
  "country_iso3": "CHN",
  "location": {
    "lat": 42.894,
    "lon": 130.291,
    "precision": "site"
  },
  "types": [
    "smelter"
  ],
  "commodities": [
    {
      "metal": "Copper",
      "primary": true
    }
  ],
  "status": "unknown",
  "company_mentions": [],
  "products": [],
  "sources": [
    {
      "type": "csv_import",
      "id": "Mines.csv Run 1",
      "date": "2025-10-20T15:29:44.020956"
    }
  ],
  "verification": {
    "status": "csv_imported",
    "confidence": 0.8,
    "last_checked": "2025-11-04T19:18:46.635806Z",
    "checked_by": "import_pipeline",
    "notes": "Canonical name+slug generated"
  },
  "canonical_name": "Zijin Smelter",
  "canonical_slug": "zijin-smelter",
  "display_name": "Zijin",
  "primary_type": "smelter",
  "type_confidence": 1.0,
  "data_quality": {
    "canonicalization_confidence": 0.615,
    "flags": {
      "town_missing": true,
      "operator_unresolved": false,
      "canonical_name_incomplete": true
    }
  },
  "display_name_source": "auto"
}