{
  "facility_id": "chn-baiyinhua-no-2-surface-mine-fac",
  "name": "Baiyinhua No. 2 Surface Mine",
  "aliases": [
    "Baiyinhua No. 2 Surface Mine",
    "Xingan",
    "Xingye"
  ],
  "country_iso3": "CHN",
  "location": {
    "lat": 44.81,
    "lon": 118.485,
    "precision": "site"
  },
  "types": [
    "mine"
  ],
  "commodities": [
    {
      "metal": "coal",
      "primary": true
    }
  ],
  "status": "unknown",
  "company_mentions": [],
  "products": [],
  "sources": [
    {
      "type": "csv_import",
      "id": "Mines.csv Run 1",
      "date": "2025-10-20T15:27:44.398252"
    }
  ],
  "verification": {
    "status": "csv_imported",
    "confidence": 0.8,
    "last_checked": "2025-10-20T15:27:44.398264",
    "checked_by": "import_pipeline",
    "notes": null
  },
  "canonical_name": "Baiyinhua No. 2 Surface Mine",
  "canonical_slug": "baiyinhua-no-2-surface-mine",
  "display_name": "Baiyinhua No. 2 Surface",
  "primary_type": "mine",
  "type_confidence": 0.95,
  "data_quality": {
    "canonicalization_confidence": 0.6,
    "flags": {
      "town_missing": true,
      "operator_unresolved": true
    }
  }
}
