{
  "facility_id": "chn-xiaoyu-coal-mine-fac",
  "name": "Xiaoyu Coal Mine",
  "aliases": [
    "Xiaoyu Coal Mine",
    "Xiaoyu"
  ],
  "country_iso3": "CHN",
  "location": {
    "lat": 39.815,
    "lon": 112.898,
    "precision": "site"
  },
  "types": [
    "mine"
  ],
  "commodities": [
    {
      "metal": "thermal coal",
      "primary": true
    }
  ],
  "status": "unknown",
  "company_mentions": [
    "Yanzhou Coal Mining Company Limited"
  ],
  "products": [],
  "sources": [
    {
      "type": "csv_import",
      "id": "Mines.csv Run 1",
      "date": "2025-10-20T15:28:16.899630"
    }
  ],
  "verification": {
    "status": "csv_imported",
    "confidence": 0.8,
    "last_checked": "2025-11-04T19:18:46.867034Z",
    "checked_by": "import_pipeline",
    "notes": "Canonical name+slug generated"
  },
  "canonical_name": "Xiaoyu Coal Mine",
  "canonical_slug": "xiaoyu-coal-mine",
  "display_name": "Xiaoyu Coal",
  "primary_type": "mine",
  "type_confidence": 1.0,
  "data_quality": {
    "canonicalization_confidence": 0.615,
    "flags": {
      "town_missing": true,
      "operator_unresolved": false,
      "canonical_name_incomplete": true
    }
  },
  "display_name_source": "auto",
  "province": "Shandong Province",
  "enrichment_notes": {
    "web_search_companies": {
      "timestamp": "2025-11-30T21:05:55.000000Z",
      "operators": [
        "Yanzhou Coal Mining Company Limited"
      ],
      "owners": [
        "Yanzhou Coal Mining Company Limited"
      ],
      "notes": "Yanzhou Coal Mining Company Limited is the primary operator and owner of the Xiaoyu Coal Mine."
    }
  }
}