{
  "facility_id": "chn-hunan-zhouyuanshan-coal-mine-fac",
  "name": "Hunan Zhouyuanshan Coal Mine",
  "aliases": [
    "Hunan Zhouyuanshan Coal Mine",
    "Zixing"
  ],
  "country_iso3": "CHN",
  "location": {
    "lat": 26.015,
    "lon": 113.27,
    "precision": "site"
  },
  "types": [
    "mine"
  ],
  "commodities": [
    {
      "metal": "coal",
      "primary": true
    }
  ],
  "status": "unknown",
  "company_mentions": [],
  "products": [],
  "sources": [
    {
      "type": "csv_import",
      "id": "Mines.csv Run 1",
      "date": "2025-10-20T15:28:56.779306"
    }
  ],
  "verification": {
    "status": "csv_imported",
    "confidence": 0.8,
    "last_checked": "2025-10-20T15:28:56.779317",
    "checked_by": "import_pipeline",
    "notes": null
  }
}