{
  "facility_id": "chn-fuli-coal-mine-fac",
  "name": "Fuli Coal Mine",
  "aliases": [
    "Fuli Coal Mine",
    "Xinlu Coal Mine",
    "Fuli",
    "Nanshan"
  ],
  "country_iso3": "CHN",
  "location": {
    "lat": 47.285,
    "lon": 130.292,
    "precision": "site"
  },
  "types": [
    "mine"
  ],
  "commodities": [
    {
      "metal": "metallurgical coal",
      "primary": true
    }
  ],
  "status": "unknown",
  "company_mentions": [
    "Heilongjiang Hegang Mining Co., Ltd.",
    "Longmay Mining Holding Group"
  ],
  "products": [],
  "sources": [
    {
      "type": "csv_import",
      "id": "Mines.csv Run 1",
      "date": "2025-10-20T15:28:11.378843"
    }
  ],
  "verification": {
    "status": "csv_imported",
    "confidence": 0.8,
    "last_checked": "2025-11-04T19:18:46.762041Z",
    "checked_by": "import_pipeline",
    "notes": "Canonical name+slug generated"
  },
  "canonical_name": "Fuli Coal Mine",
  "canonical_slug": "fuli-coal-mine",
  "display_name": "Fuli Coal",
  "primary_type": "mine",
  "type_confidence": 1.0,
  "data_quality": {
    "canonicalization_confidence": 0.615,
    "flags": {
      "town_missing": true,
      "operator_unresolved": false,
      "canonical_name_incomplete": true
    }
  },
  "display_name_source": "auto",
  "province": "Heilongjiang",
  "enrichment_notes": {
    "web_search_companies": {
      "timestamp": "2025-12-01T17:24:49.000000Z",
      "operators": [
        "Heilongjiang Hegang Mining Co., Ltd."
      ],
      "owners": [
        "Longmay Mining Holding Group"
      ],
      "notes": "The mine is owned by Longmay Mining Holding Group, which is the largest coal company in northeastern China."
    }
  }
}