{
  "facility_id": "bol-la-reyna-fac",
  "name": "La Reyna",
  "aliases": [],
  "country_iso3": "BOL",
  "location": {
    "lat": -18.098,
    "lon": -66.9,
    "precision": "site"
  },
  "types": [
    "mine"
  ],
  "commodities": [
    {
      "metal": "tin",
      "primary": true
    }
  ],
  "status": "unknown",
  "company_mentions": [
    "Angel Wing Metals Inc.",
    "Lago de Oro Resources, SA de CV"
  ],
  "products": [],
  "sources": [
    {
      "type": "csv_import",
      "id": "Mines.csv Run 1",
      "date": "2025-10-20T15:26:19.106646"
    }
  ],
  "verification": {
    "status": "csv_imported",
    "confidence": 0.3,
    "last_checked": "2025-11-04T19:18:57.448586Z",
    "checked_by": "import_pipeline",
    "notes": "Canonical name+slug generated"
  },
  "canonical_name": "La Reyna Mine",
  "canonical_slug": "la-reyna-mine",
  "display_name": "La Reyna",
  "primary_type": "mine",
  "type_confidence": 1.0,
  "data_quality": {
    "canonicalization_confidence": 0.51,
    "flags": {
      "town_missing": true,
      "operator_unresolved": false,
      "canonical_name_incomplete": true
    }
  },
  "display_name_source": "auto",
  "province": "Nayarit",
  "enrichment_notes": {
    "web_search_companies": {
      "timestamp": "2025-11-26T10:02:50.000000Z",
      "operators": [
        "Angel Wing Metals Inc."
      ],
      "owners": [
        "Lago de Oro Resources, SA de CV"
      ],
      "notes": "Angel Wing Metals has acquired a 100% interest in the La Reyna claim group."
    }
  }
}