{
  "facility_id": "fji-ba-delta-ironsands-fac",
  "name": "**Ba Delta Ironsands**",
  "aliases": [],
  "country_iso3": "FJI",
  "location": {
    "lat": null,
    "lon": null,
    "precision": "unknown"
  },
  "types": [
    "operating project"
  ],
  "commodities": [],
  "status": "operating",
  "company_mentions": [],
  "products": [],
  "sources": [
    {
      "type": "csv_import",
      "id": "Research Import FJI 2025-10-28",
      "date": "2025-10-28T17:05:12.184695"
    }
  ],
  "verification": {
    "status": "csv_imported",
    "confidence": 0.5,
    "last_checked": "2025-10-28T17:05:12.184696",
    "checked_by": "import_pipeline",
    "notes": null
  },
  "canonical_name": "**Ba Delta Ironsands**",
  "canonical_slug": "ba-delta-ironsands-facility",
  "display_name": "**Ba Delta Ironsands**",
  "primary_type": "facility",
  "type_confidence": 0.3,
  "data_quality": {
    "canonicalization_confidence": 0.3,
    "flags": {
      "town_missing": true,
      "operator_unresolved": true,
      "canonical_name_incomplete": true
    }
  }
}
