{
  "facility_id": "bra-morro-agudo-fac",
  "name": "Morro Agudo",
  "aliases": [
    "Morro Agudo",
    "Paracatuzn",
    "Morro Agudo",
    "Morro Agudo"
  ],
  "country_iso3": "BRA",
  "location": {
    "lat": -17.495,
    "lon": -46.817,
    "precision": "site"
  },
  "types": [
    "mine"
  ],
  "commodities": [
    {
      "metal": "Zinc",
      "primary": true
    },
    {
      "metal": "Silver",
      "primary": false
    },
    {
      "metal": "Gold",
      "primary": false
    },
    {
      "metal": "Cadmium",
      "primary": false
    }
  ],
  "status": "unknown",
  "company_mentions": [],
  "products": [],
  "sources": [
    {
      "type": "csv_import",
      "id": "Mines.csv Run 1",
      "date": "2025-10-20T15:26:18.646843"
    }
  ],
  "verification": {
    "status": "csv_imported",
    "confidence": 0.8,
    "last_checked": "2025-10-20T15:26:18.646851",
    "checked_by": "import_pipeline",
    "notes": null
  }
}