{
  "facility_id": "bra-sao-luis-iron-ore-pellet-operation-fac",
  "name": "Sao Luis Iron Ore Pellet Operation",
  "aliases": [
    "Sao Luis Iron Ore Pellet Operation",
    "Sao Luis Pellets",
    "Sao Luis Pellet Plant"
  ],
  "country_iso3": "BRA",
  "location": {
    "lat": -2.563,
    "lon": -44.348,
    "precision": "site"
  },
  "types": [
    "mine",
    "plant"
  ],
  "commodities": [
    {
      "metal": "Iron Ore",
      "primary": true,
      "chemical_formula": "Fe2O3/Fe3O4"
    }
  ],
  "status": "unknown",
  "company_mentions": [],
  "products": [],
  "sources": [
    {
      "type": "csv_import",
      "id": "Mines.csv Run 1",
      "date": "2025-10-20T15:27:37.417854"
    }
  ],
  "verification": {
    "status": "csv_imported",
    "confidence": 0.8,
    "last_checked": "2025-10-20T15:27:37.417858",
    "checked_by": "import_pipeline",
    "notes": null
  },
  "canonical_name": "Sao Luis Iron Ore Pellet Mine",
  "canonical_slug": "sao-luis-iron-ore-pellet-mine",
  "display_name": "Sao Luis Iron Ore Pellet",
  "primary_type": "mine",
  "type_confidence": 0.95,
  "data_quality": {
    "canonicalization_confidence": 0.6,
    "flags": {
      "town_missing": true,
      "operator_unresolved": true
    }
  }
}
