{
  "facility_id": "cod-mutoshi-fac",
  "name": "Mutoshi",
  "aliases": [
    "Mutoshi",
    "Mutoshi"
  ],
  "country_iso3": "COD",
  "location": {
    "lat": -10.676,
    "lon": 25.535,
    "precision": "site"
  },
  "types": [
    "mine"
  ],
  "commodities": [
    {
      "metal": "copper",
      "primary": true
    },
    {
      "metal": "cobalt",
      "primary": false
    }
  ],
  "status": "unknown",
  "owner_links": [],
  "operator_link": null,
  "products": [],
  "sources": [
    {
      "type": "mines_csv",
      "row": 2313
    }
  ],
  "verification": {
    "status": "csv_imported",
    "confidence": 0.65,
    "last_checked": "2025-10-12T19:43:43.783955",
    "checked_by": "migration_script"
  }
}