{
  "facility_id": "mys-msc-smelters-fac",
  "name": "MSC Smelters",
  "aliases": [],
  "country_iso3": "MYS",
  "location": {
    "lat": 5.438,
    "lon": 100.388,
    "precision": "city"
  },
  "types": [
    "plant"
  ],
  "commodities": [
    {
      "metal": "tin",
      "primary": true
    }
  ],
  "status": "operating",
  "company_mentions": [
    "Malaysia Smelting Corporation Berhad",
    "Rahman Hydraulic Tin Sdn. Bhd."
  ],
  "products": [],
  "sources": [
    {
      "type": "csv_import",
      "id": "Research Import MYS 2025-10-29",
      "date": "2025-10-29T22:11:17.292679"
    }
  ],
  "verification": {
    "status": "web_search_geocoded",
    "confidence": 0.75,
    "last_checked": "2025-12-18T14:23:57Z",
    "checked_by": "manual_geocoding",
    "notes": "Canonical name+slug generated | [NULL-ISLAND-FIX 2025-12-18T14:23:57Z] Butterworth smelter location in Perak."
  },
  "canonical_name": "MSC Smelters Smelter",
  "canonical_slug": "msc-smelters-smelter",
  "display_name": "MSC Smelters",
  "primary_type": "smelter",
  "type_confidence": 1.0,
  "data_quality": {
    "canonicalization_confidence": 0.51,
    "flags": {
      "town_missing": true,
      "operator_unresolved": true,
      "canonical_name_incomplete": false
    }
  },
  "display_name_source": "auto",
  "province": "Perak",
  "enrichment_notes": {
    "web_search_companies": {
      "timestamp": "2025-12-02T08:36:05.000000Z",
      "operators": [
        "Rahman Hydraulic Tin Sdn. Bhd."
      ],
      "owners": [
        "Malaysia Smelting Corporation Berhad"
      ],
      "notes": "MSC owns Rahman Hydraulic Tin Sdn. Bhd. and has expanded its operations through acquisitions."
    }
  }
}
