{
  "facility_id": "can-north-star-mine-fac",
  "name": "North Star Mine",
  "aliases": [
    "North Star Mine",
    "Creighton Mine",
    "Creighton Mine",
    "Creighton Mine",
    "Creighton",
    "Gertrude"
  ],
  "country_iso3": "CAN",
  "location": {
    "lat": 46.462,
    "lon": -81.184,
    "precision": "site"
  },
  "types": [
    "mine"
  ],
  "commodities": [
    {
      "metal": "Nickel",
      "primary": true
    },
    {
      "metal": "Gold",
      "primary": false
    },
    {
      "metal": "Cobalt",
      "primary": false
    }
  ],
  "status": "unknown",
  "company_mentions": [],
  "products": [],
  "sources": [
    {
      "type": "csv_import",
      "id": "Mines.csv Run 1",
      "date": "2025-10-20T15:26:40.438610"
    }
  ],
  "verification": {
    "status": "csv_imported",
    "confidence": 0.65,
    "last_checked": "2025-11-04T19:18:50.752920Z",
    "checked_by": "import_pipeline",
    "notes": "Canonical name+slug generated"
  },
  "canonical_name": "North Star Mine",
  "canonical_slug": "north-star-mine",
  "display_name": "North Star",
  "primary_type": "mine",
  "type_confidence": 1.0,
  "data_quality": {
    "canonicalization_confidence": 0.615,
    "flags": {
      "town_missing": true,
      "operator_unresolved": false,
      "canonical_name_incomplete": true
    }
  },
  "display_name_source": "auto"
}
