{
  "facility_id": "can-deschambault-aluminium-smelter-fac",
  "name": "Deschambault Aluminium Smelter",
  "aliases": [
    "Deschambault Aluminium Smelter",
    "Deschambault",
    "Deschambault Smelter"
  ],
  "country_iso3": "CAN",
  "location": {
    "lat": 46.693,
    "lon": -71.947,
    "precision": "site"
  },
  "types": [
    "smelter"
  ],
  "commodities": [
    {
      "metal": "aluminum",
      "primary": true
    }
  ],
  "status": "unknown",
  "company_mentions": [],
  "products": [],
  "sources": [
    {
      "type": "csv_import",
      "id": "Mines.csv Run 1",
      "date": "2025-10-20T15:27:23.149825"
    }
  ],
  "verification": {
    "status": "csv_imported",
    "confidence": 0.8,
    "last_checked": "2025-11-04T19:18:50.747326Z",
    "checked_by": "import_pipeline",
    "notes": "Canonical name+slug generated"
  },
  "canonical_name": "Deschambault Aluminium Smelter",
  "canonical_slug": "deschambault-aluminium-smelter",
  "display_name": "Deschambault Aluminium",
  "primary_type": "smelter",
  "type_confidence": 1.0,
  "data_quality": {
    "canonicalization_confidence": 0.615,
    "flags": {
      "town_missing": true,
      "operator_unresolved": false,
      "canonical_name_incomplete": true
    }
  },
  "display_name_source": "auto"
}
