{
  "facility_id": "zaf-umlabu-colliery-fac",
  "name": "Umlabu Colliery",
  "aliases": [
    "Umlabu Colliery",
    "Umlabu Colliery"
  ],
  "country_iso3": "ZAF",
  "location": {
    "lat": -26.381,
    "lon": 29.99,
    "precision": "site"
  },
  "types": [
    "mine"
  ],
  "commodities": [
    {
      "metal": "coal",
      "primary": true
    }
  ],
  "status": "unknown",
  "products": [],
  "sources": [
    {
      "type": "mines_csv",
      "row": 5016
    }
  ],
  "verification": {
    "status": "csv_imported",
    "confidence": 0.85,
    "last_checked": "2025-10-12T19:43:44.213825",
    "checked_by": "migration_script"
  }
}