{
  "facility_id": "mmr-pagaye-mine-fac",
  "name": "Pagaye Mine",
  "aliases": [],
  "country_iso3": "MMR",
  "location": {
    "lat": 14.1,
    "lon": 98.5,
    "precision": "site"
  },
  "types": [
    "mine"
  ],
  "commodities": [
    {
      "metal": "tin",
      "primary": true
    }
  ],
  "status": "unknown",
  "products": [],
  "sources": [
    {
      "type": "mines_csv",
      "row": 2179
    }
  ],
  "verification": {
    "status": "csv_imported",
    "confidence": 0.2,
    "last_checked": "2025-10-12T19:43:43.555800",
    "checked_by": "migration_script"
  }
}