{
  "facility_id": "usa-clearfield-county-strips-pa-rhdc-fac",
  "name": "Clearfield County Strips (PA RHDC)",
  "aliases": [
    "Clearfield County Strips (PA RHDC)",
    "Finney Strips"
  ],
  "country_iso3": "USA",
  "location": {
    "lat": 40.838,
    "lon": -78.36,
    "precision": "site"
  },
  "types": [
    "mine"
  ],
  "commodities": [
    {
      "metal": "coal",
      "primary": true
    }
  ],
  "status": "unknown",
  "products": [],
  "sources": [
    {
      "type": "mines_csv",
      "row": 6944
    }
  ],
  "verification": {
    "status": "csv_imported",
    "confidence": 0.65,
    "last_checked": "2025-10-12T19:43:44.247590",
    "checked_by": "migration_script"
  }
}