{
  "facility_id": "usa-jeffrey-hwm-mine-fac",
  "name": "Jeffrey HWM Mine",
  "aliases": [],
  "country_iso3": "USA",
  "location": {
    "lat": 36.936,
    "lon": -82.713,
    "precision": "site"
  },
  "types": [
    "mine"
  ],
  "commodities": [
    {
      "metal": "coal",
      "primary": true
    }
  ],
  "status": "unknown",
  "products": [],
  "sources": [
    {
      "type": "mines_csv",
      "row": 5601
    }
  ],
  "verification": {
    "status": "csv_imported",
    "confidence": 0.65,
    "last_checked": "2025-10-12T19:43:44.239089",
    "checked_by": "migration_script"
  }
}