{
  "facility_id": "usa-huntington-alloys-rolling-mill-fac",
  "name": "Huntington Alloys Rolling Mill",
  "aliases": [],
  "country_iso3": "USA",
  "location": {
    "lat": 38.415,
    "lon": -82.457,
    "precision": "site"
  },
  "types": [
    "plant"
  ],
  "commodities": [
    {
      "metal": "Nickel",
      "primary": true
    }
  ],
  "status": "unknown",
  "company_mentions": [
    "Berkshire Hathaway",
    "Precision Castparts Corporation",
    "Special Metals Corporation"
  ],
  "products": [],
  "sources": [
    {
      "type": "csv_import",
      "id": "Mines.csv Run 1",
      "date": "2025-10-20T15:26:34.034644"
    }
  ],
  "verification": {
    "status": "csv_imported",
    "confidence": 0.3,
    "last_checked": "2025-11-04T19:18:45.748172Z",
    "checked_by": "import_pipeline",
    "notes": "Canonical name+slug generated"
  },
  "canonical_name": "Huntington Alloys Rolling Plant",
  "canonical_slug": "huntington-alloys-rolling-plant",
  "display_name": "Huntington Alloys Rolling",
  "primary_type": "plant",
  "type_confidence": 1.0,
  "data_quality": {
    "canonicalization_confidence": 0.615,
    "flags": {
      "town_missing": true,
      "operator_unresolved": false,
      "canonical_name_incomplete": true
    }
  },
  "display_name_source": "auto",
  "province": "West Virginia",
  "enrichment_notes": {
    "web_search_companies": {
      "timestamp": "2025-12-01T20:24:39.000000Z",
      "operators": [
        "Special Metals Corporation"
      ],
      "owners": [
        "Berkshire Hathaway",
        "Precision Castparts Corporation"
      ],
      "notes": "Special Metals Corporation operates the facility, which was previously owned by INCO before being acquired by Special Metals."
    }
  }
}