{
  "facility_id": "usa-darby-fac",
  "name": "Darby",
  "aliases": [
    "Darby",
    "D 30 Clover Fork Coal Mine",
    "D 29 Darby Fork Coal Mine",
    "D 5 Mine",
    "Highsplint #1",
    "K 4 Mine",
    "Mine #1 (KY PME)",
    "Rex Strip #1",
    "Harlan County",
    "Mine No 1",
    "Powell Mountain",
    "Darby",
    "Limestone",
    "ICG No 1 (Powell Mountain)",
    "Kentucky Wallins"
  ],
  "country_iso3": "USA",
  "location": {
    "lat": 36.877,
    "lon": -83.044,
    "precision": "site"
  },
  "types": [
    "mine"
  ],
  "commodities": [
    {
      "metal": "coal",
      "primary": true
    }
  ],
  "status": "unknown",
  "company_mentions": [],
  "products": [],
  "sources": [
    {
      "type": "csv_import",
      "id": "Mines.csv Run 1",
      "date": "2025-10-20T15:27:22.864332"
    }
  ],
  "verification": {
    "status": "csv_imported",
    "confidence": 0.8,
    "last_checked": "2025-11-04T19:18:45.755351Z",
    "checked_by": "import_pipeline",
    "notes": "Canonical name+slug generated"
  },
  "canonical_name": "Darby Mine",
  "canonical_slug": "darby-mine",
  "display_name": "Darby",
  "primary_type": "mine",
  "type_confidence": 1.0,
  "data_quality": {
    "canonicalization_confidence": 0.51,
    "flags": {
      "town_missing": true,
      "operator_unresolved": false,
      "canonical_name_incomplete": true
    }
  },
  "display_name_source": "auto"
}
