{
  "facility_id": "usa-the-casselman-surface-mine-fac",
  "name": "The Casselman Surface Mine",
  "aliases": [],
  "country_iso3": "USA",
  "location": {
    "lat": 39.889,
    "lon": -79.213,
    "precision": "site"
  },
  "types": [
    "mine"
  ],
  "commodities": [
    {
      "metal": "coal",
      "primary": true
    }
  ],
  "status": "unknown",
  "owner_links": [],
  "operator_link": null,
  "products": [],
  "sources": [
    {
      "type": "mines_csv",
      "row": 6193
    }
  ],
  "verification": {
    "status": "csv_imported",
    "confidence": 0.65,
    "last_checked": "2025-10-12T19:43:44.242664",
    "checked_by": "migration_script"
  }
}