{
  "facility_id": "kaz-maleyevsky-mine-fac",
  "name": "Maleyevsky Mine",
  "aliases": [],
  "country_iso3": "KAZ",
  "location": {
    "lat": null,
    "lon": null,
    "precision": "unknown"
  },
  "types": [
    "mine"
  ],
  "commodities": [
    {
      "metal": "Zinc",
      "primary": true
    }
  ],
  "status": "operating",
  "company_mentions": [],
  "products": [],
  "sources": [
    {
      "type": "csv_import",
      "id": "Kazakhstan Deep Research Report 2025",
      "date": "2025-10-21T09:03:08.700340"
    }
  ],
  "verification": {
    "status": "csv_imported",
    "confidence": 0.5,
    "last_checked": "2025-10-21T09:03:08.700347",
    "checked_by": "import_pipeline",
    "notes": null
  },
  "canonical_name": "Maleyevsky Mine",
  "canonical_slug": "maleyevsky-mine",
  "display_name": "Maleyevsky",
  "primary_type": "mine",
  "type_confidence": 0.95,
  "data_quality": {
    "canonicalization_confidence": 0.6,
    "flags": {
      "town_missing": true,
      "operator_unresolved": true
    }
  }
}
