{
  "facility_id": "mkd-ilovica-shtuka-project-fac",
  "name": "Ilovica-Shtuka Project",
  "aliases": [],
  "country_iso3": "MKD",
  "location": {
    "lat": 41.437,
    "lon": 22.643,
    "precision": "region"
  },
  "types": [
    "plant"
  ],
  "commodities": [
    {
      "metal": "copper",
      "primary": true
    },
    {
      "metal": "gold",
      "primary": false
    },
    {
      "metal": "silver",
      "primary": false
    },
    {
      "metal": "molybdenum",
      "primary": false
    }
  ],
  "status": "unknown",
  "company_mentions": [
    "Euromax Resources Ltd"
  ],
  "products": [],
  "sources": [
    {
      "type": "csv_import",
      "id": "Research Import CMR 2025-10-29",
      "date": "2025-10-29T22:50:53.926491"
    }
  ],
  "verification": {
    "status": "web_search_geocoded",
    "confidence": 0.6,
    "last_checked": "2025-12-18T14:09:45Z",
    "checked_by": "manual_geocoding",
    "notes": "Canonical name+slug generated | [NULL-ISLAND-FIX 2025-12-18T14:09:45Z] Euromax Resources copper-gold porphyry project in Bosilovo, 15km NE of Strumica."
  },
  "canonical_name": "Ilovica Shtuka Development",
  "canonical_slug": "ilovica-shtuka-development",
  "display_name": "Ilovica Shtuka",
  "primary_type": "development",
  "type_confidence": 1.0,
  "data_quality": {
    "canonicalization_confidence": 0.615,
    "flags": {
      "town_missing": true,
      "operator_unresolved": false,
      "canonical_name_incomplete": false
    }
  },
  "canonical_name_history": [
    {
      "name": "Ilovica-Shtuka Development",
      "from": "2025-10-29T22:50:53.926521",
      "to": "2025-11-04T19:19:06.909611Z",
      "reason": "data_correction"
    }
  ],
  "display_name_source": "auto",
  "province": "Macedonia",
  "enrichment_notes": {
    "web_search_companies": {
      "timestamp": "2025-12-02T08:53:14.000000Z",
      "operators": [
        "Euromax Resources Ltd"
      ],
      "owners": [
        "Euromax Resources Ltd"
      ],
      "notes": "Euromax Resources is focused on developing the Ilovica-Shtuka Project, which is the largest mining project in North Macedonia."
    }
  }
}
