{
  "facility_id": "zmb-konkola-fac",
  "name": "Konkola",
  "aliases": [],
  "country_iso3": "ZMB",
  "location": {
    "lat": -12.322,
    "lon": 27.79,
    "precision": "site"
  },
  "types": [
    "mine"
  ],
  "commodities": [
    {
      "metal": "Copper",
      "primary": true
    }
  ],
  "status": "unknown",
  "company_mentions": [],
  "products": [],
  "sources": [
    {
      "type": "csv_import",
      "id": "Mines.csv Run 1",
      "date": "2025-10-20T15:27:11.429673"
    }
  ],
  "verification": {
    "status": "csv_imported",
    "confidence": 0.3,
    "last_checked": "2025-10-20T15:27:11.429679",
    "checked_by": "import_pipeline",
    "notes": null
  },
  "canonical_name": "Konkola Mine",
  "canonical_slug": "konkola-mine",
  "display_name": "Konkola",
  "primary_type": "mine",
  "type_confidence": 0.95,
  "data_quality": {
    "canonicalization_confidence": 0.495,
    "flags": {
      "town_missing": true,
      "operator_unresolved": true,
      "canonical_name_incomplete": true
    }
  }
}
