{
  "facility_id": "aus-csa-cobar-mine-fac",
  "name": "Csa Cobar Mine",
  "aliases": [],
  "country_iso3": "AUS",
  "location": {
    "lat": -32.167,
    "lon": 147.012,
    "precision": "site"
  },
  "types": [
    "mine"
  ],
  "commodities": [
    {
      "metal": "Copper",
      "primary": true
    },
    {
      "metal": "Lead",
      "primary": false
    },
    {
      "metal": "Platinum",
      "primary": false
    },
    {
      "metal": "tin",
      "primary": false
    },
    {
      "metal": "Zinc",
      "primary": false
    }
  ],
  "status": "unknown",
  "company_mentions": [],
  "products": [],
  "sources": [
    {
      "type": "csv_import",
      "id": "Mines.csv Run 1",
      "date": "2025-10-20T15:26:55.579623"
    }
  ],
  "verification": {
    "status": "csv_imported",
    "confidence": 0.3,
    "last_checked": "2025-11-04T19:18:52.274166Z",
    "checked_by": "import_pipeline",
    "notes": "Canonical name+slug generated"
  },
  "canonical_name": "Csa Cobar Mine",
  "canonical_slug": "csa-cobar-mine",
  "display_name": "Csa Cobar",
  "primary_type": "mine",
  "type_confidence": 1.0,
  "data_quality": {
    "canonicalization_confidence": 0.615,
    "flags": {
      "town_missing": true,
      "operator_unresolved": false,
      "canonical_name_incomplete": true
    }
  },
  "display_name_source": "auto"
}
