{
  "facility_id": "aus-leichhardt-mt-watson-fac",
  "name": "Leichhardt (Mt Watson)",
  "aliases": [
    "Mount Cuthbert",
    "Leichhardt (Mt Watson)",
    "Leichhardt"
  ],
  "country_iso3": "AUS",
  "location": {
    "lat": -19.99,
    "lon": 139.914,
    "precision": "site"
  },
  "types": [
    "mine"
  ],
  "commodities": [
    {
      "metal": "copper",
      "primary": true
    },
    {
      "metal": "gold",
      "primary": false
    },
    {
      "metal": "silver",
      "primary": false
    }
  ],
  "status": "unknown",
  "products": [],
  "sources": [
    {
      "type": "mines_csv",
      "row": 1589
    }
  ],
  "verification": {
    "status": "csv_imported",
    "confidence": 0.85,
    "last_checked": "2025-10-12T19:43:43.338108",
    "checked_by": "migration_script"
  }
}