{
  "facility_id": "aus-atlas-iron-sanjiv-ridge-mine-fac",
  "name": "Atlas Iron Sanjiv Ridge Mine",
  "aliases": [],
  "country_iso3": "AUS",
  "location": {
    "lat": -21.474,
    "lon": 119.665,
    "precision": "site"
  },
  "types": [
    "mine"
  ],
  "commodities": [
    {
      "metal": "Iron Ore",
      "primary": true,
      "chemical_formula": "Fe2O3/Fe3O4"
    }
  ],
  "status": "unknown",
  "company_mentions": [],
  "products": [],
  "sources": [
    {
      "type": "csv_import",
      "id": "Mines.csv Run 1",
      "date": "2025-10-20T15:29:17.856458"
    }
  ],
  "verification": {
    "status": "csv_imported",
    "confidence": 0.65,
    "last_checked": "2025-11-04T19:18:52.235112Z",
    "checked_by": "import_pipeline",
    "notes": "Canonical name+slug generated"
  },
  "canonical_name": "Atlas Iron Sanjiv Ridge Mine",
  "canonical_slug": "atlas-iron-sanjiv-ridge-mine",
  "display_name": "Atlas Iron Sanjiv Ridge",
  "primary_type": "mine",
  "type_confidence": 1.0,
  "data_quality": {
    "canonicalization_confidence": 0.615,
    "flags": {
      "town_missing": true,
      "operator_unresolved": false,
      "canonical_name_incomplete": true
    }
  },
  "display_name_source": "auto"
}
