{
  "facility_id": "aus-mungari-fac",
  "name": "Mungari",
  "aliases": [
    "White Foil",
    "Hornet",
    "Raleigh U/G",
    "U/G",
    "Pegasus",
    "Portal",
    "Millennium",
    "Kundana",
    "Northern Star Kalgoorlie Operations",
    "Mungari",
    "Mungari"
  ],
  "country_iso3": "AUS",
  "location": {
    "lat": -30.741,
    "lon": 121.249,
    "precision": "site"
  },
  "types": [
    "mine"
  ],
  "commodities": [
    {
      "metal": "Gold",
      "primary": true
    },
    {
      "metal": "Zinc",
      "primary": false
    }
  ],
  "status": "unknown",
  "company_mentions": [],
  "products": [],
  "sources": [
    {
      "type": "csv_import",
      "id": "Mines.csv Run 1",
      "date": "2025-10-20T15:26:59.192469"
    }
  ],
  "verification": {
    "status": "csv_imported",
    "confidence": 0.8,
    "last_checked": "2025-11-04T19:18:52.261107Z",
    "checked_by": "import_pipeline",
    "notes": "Canonical name+slug generated"
  },
  "canonical_name": "Mungari Mine",
  "canonical_slug": "mungari-mine",
  "display_name": "Mungari",
  "primary_type": "mine",
  "type_confidence": 1.0,
  "data_quality": {
    "canonicalization_confidence": 0.51,
    "flags": {
      "town_missing": true,
      "operator_unresolved": false,
      "canonical_name_incomplete": true
    }
  },
  "display_name_source": "auto"
}
